heyyz/__init__.py
heyyz/__version__.py
heyyz/core.py
heyyz/dbf_utils.py
heyyz-0.1.9.dist-info/LICENSE
heyyz-0.1.9.dist-info/METADATA
heyyz-0.1.9.dist-info/WHEEL
heyyz-0.1.9.dist-info/top_level.txt
heyyz-0.1.9.dist-info/RECORD
