Metadata-Version: 2.1
Name: heyyz
Version: 0.1.9
Summary: Utilities for yz work.
Home-page: https://github.com/CarlHey/heyyz
Author: heyy
Author-email: hey.ing@qq.com
License: MIT
Platform: UNKNOWN
Classifier: License :: OSI Approved :: MIT License
Classifier: Programming Language :: Python
Classifier: Programming Language :: Python :: 3
Classifier: Programming Language :: Python :: 3.7
Classifier: Programming Language :: Python :: Implementation :: CPython
Classifier: Programming Language :: Python :: Implementation :: PyPy
Requires-Python: >=3.7.0
